README.rst
setup.py
statx/__init__.py
statx/base.py
statx.egg-info/PKG-INFO
statx.egg-info/SOURCES.txt
statx.egg-info/dependency_links.txt
statx.egg-info/pbr.json
statx.egg-info/requires.txt
statx.egg-info/top_level.txt