Metadata-Version: 1.1
Name: statx
Version: 0.0.2
Summary: A tool to count things
Home-page: https://github.com/lorien/statx
Author: Gregory Petukhov
Author-email: lorien@lorien.name
License: MIT
Keywords: stat statistics stats
Platform: UNKNOWN
Classifier: Programming Language :: Python
Classifier: Programming Language :: Python :: 2
Classifier: Programming Language :: Python :: 3
Classifier: License :: OSI Approved :: MIT License
Classifier: Development Status :: 5 - Production/Stable
Classifier: Intended Audience :: Developers
Classifier: Operating System :: OS Independent
Classifier: Topic :: Software Development :: Libraries :: Python Modules
Classifier: Topic :: Software Development :: Libraries
